src/clock_divider.v
`timescale 1ns/1ps
// DIVISOR must be an even integer >= 2.
// divided is an observation output; use tick as an enable on clk.
module clock_divider #(parameter integer DIVISOR = 10) (
    input wire clk, rst,
    output reg divided,
    output wire tick
);
    localparam integer WIDTH = $clog2(DIVISOR);
    reg [WIDTH-1:0] count;
    assign tick = !rst && (count == DIVISOR - 1);
    always @(posedge clk) begin
        if (rst) begin
            count <= 0;
            divided <= 1'b0;
        end else begin
            if (count == DIVISOR - 1) count <= 0;
            else count <= count + 1'b1;
            if (count == DIVISOR/2 - 1) divided <= 1'b1;
            else if (count == DIVISOR - 1) divided <= 1'b0;
        end
    end
endmodule

sim/tb_clock_divider.sv
`timescale 1ns/1ps
module tb_clock_divider;
    reg clk = 0, rst = 1;
    integer checks = 0;
    always #5 clk = ~clk;
    task step; begin @(posedge clk); #1; end endtask
    task check(input condition, input [8*100-1:0] description);
        begin
            checks = checks + 1;
            if (condition !== 1'b1) begin
                $display("LAB2_FAIL %0s time=%0t", description, $time);
                $fatal(1, "check failed");
            end
        end
    endtask
    task finish;
        begin
            $display("LAB2_PASS clock_divider checks=%d", checks);
            $finish;
        end
    endtask
    initial begin $dumpfile("wave.vcd"); $dumpvars(0, tb_clock_divider); end
    initial begin #100000; $fatal(1, "watchdog timeout"); end
    wire divided, tick, div2, tick2;
    clock_divider #(.DIVISOR(10)) dut (clk, rst, divided, tick);
    clock_divider #(.DIVISOR(2)) minimum (clk, rst, div2, tick2);
    integer i, pulses = 0;
    always @(posedge clk) if (!rst && tick) pulses = pulses + 1;
    initial begin
        step; check({divided, tick, div2, tick2} === 4'b0000, "reset");
        rst = 0;
        for (i = 1; i <= 30; i = i + 1) begin
            step;
            check(divided === (i % 10 >= 5), "divide 10 duty and phase");
            check(tick === (i % 10 == 9), "tick before consuming edge");
            check(div2 === (i % 2 == 1), "minimum divisor duty");
            check(tick2 === (i % 2 == 1), "minimum tick");
        end
        check(pulses === 3, "three consumed enables in 30 clocks");
        repeat(7) step;
        rst = 1; #1; check(tick == 0, "reset masks tick before edge");
        step; check(divided === 0, "reset mid period");
        rst = 0;
        repeat(4) begin step; check(divided === 0, "restart low half"); end
        step; check(divided === 1, "restart first transition");
        finish;
    end
endmodule

evidence/02/vscode/wave.vcd
$date
	Thu Sep 17 13:52:33 2026
$end
$version
	Icarus Verilog
$end
$timescale
	1ps
$end
$scope module tb_clock_divider $end
$var wire 1 ! tick2 $end
$var wire 1 " tick $end
$var wire 1 # divided $end
$var wire 1 $ div2 $end
$var reg 1 % clk $end
$var reg 1 & rst $end
$var integer 32 ' checks [31:0] $end
$var integer 32 ( i [31:0] $end
$var integer 32 ) pulses [31:0] $end
$scope module dut $end
$var wire 1 % clk $end
$var wire 1 & rst $end
$var wire 1 " tick $end
$var parameter 32 * DIVISOR $end
$var parameter 32 + WIDTH $end
$var reg 4 , count [3:0] $end
$var reg 1 # divided $end
$upscope $end
$scope module minimum $end
$var wire 1 % clk $end
$var wire 1 & rst $end
$var wire 1 ! tick $end
$var parameter 32 - DIVISOR $end
$var parameter 32 . WIDTH $end
$var reg 1 / count $end
$var reg 1 $ divided $end
$upscope $end
$scope task check $end
$var reg 1 0 condition $end
$var reg 800 1 description [799:0] $end
$upscope $end
$scope task finish $end
$upscope $end
$scope task step $end
$upscope $end
$upscope $end
$enddefinitions $end
$comment Show the parameter values. $end
$dumpall
b1 .
b10 -
b100 +
b1010 *
$end
#0
$dumpvars
bx 1
x0
x/
bx ,
b0 )
bx (
b0 '
1&
0%
x$
x#
0"
0!
$end
#5000
0#
b0 ,
0$
0/
1%
#6000
b1 (
0&
b1 '
b111001001100101011100110110010101110100 1
10
#10000
0%
#15000
1!
1$
1/
b1 ,
1%
#16000
b10 (
b101 '
b11011010110100101101110011010010110110101110101011011010010000001110100011010010110001101101011 1
#20000
0%
#25000
0!
b10 ,
0$
0/
1%
#26000
b11 (
b1001 '
b11011010110100101101110011010010110110101110101011011010010000001110100011010010110001101101011 1
#30000
0%
#35000
1!
1$
1/
b11 ,
1%
#36000
b100 (
b1101 '
b11011010110100101101110011010010110110101110101011011010010000001110100011010010110001101101011 1
#40000
0%
#45000
0!
b100 ,
0$
0/
1%
#46000
b101 (
b10001 '
b11011010110100101101110011010010110110101110101011011010010000001110100011010010110001101101011 1
#50000
0%
#55000
1!
1$
1/
1#
b101 ,
1%
#56000
b110 (
b10101 '
b11011010110100101101110011010010110110101110101011011010010000001110100011010010110001101101011 1
#60000
0%
#65000
0!
b110 ,
0$
0/
1%
#66000
b111 (
b11001 '
b11011010110100101101110011010010110110101110101011011010010000001110100011010010110001101101011 1
#70000
0%
#75000
1!
1$
1/
b111 ,
1%
#76000
b1000 (
b11101 '
b11011010110100101101110011010010110110101110101011011010010000001110100011010010110001101101011 1
#80000
0%
#85000
0!
b1000 ,
0$
0/
1%
#86000
b1001 (
b100001 '
b11011010110100101101110011010010110110101110101011011010010000001110100011010010110001101101011 1
#90000
0%
#95000
1!
1"
1$
1/
b1001 ,
1%
#96000
b1010 (
b100101 '
b11011010110100101101110011010010110110101110101011011010010000001110100011010010110001101101011 1
#100000
0%
#105000
0"
0!
0#
b0 ,
0$
0/
b1 )
1%
#106000
b1011 (
b101001 '
b11011010110100101101110011010010110110101110101011011010010000001110100011010010110001101101011 1
#110000
0%
#115000
1!
1$
1/
b1 ,
1%
#116000
b1100 (
b101101 '
b11011010110100101101110011010010110110101110101011011010010000001110100011010010110001101101011 1
#120000
0%
#125000
0!
b10 ,
0$
0/
1%
#126000
b1101 (
b110001 '
b11011010110100101101110011010010110110101110101011011010010000001110100011010010110001101101011 1
#130000
0%
#135000
1!
1$
1/
b11 ,
1%
#136000
b1110 (
b110101 '
b11011010110100101101110011010010110110101110101011011010010000001110100011010010110001101101011 1
#140000
0%
#145000
0!
b100 ,
0$
0/
1%
#146000
b1111 (
b111001 '
b11011010110100101101110011010010110110101110101011011010010000001110100011010010110001101101011 1
#150000
0%
#155000
1!
1$
1/
1#
b101 ,
1%
#156000
b10000 (
b111101 '
b11011010110100101101110011010010110110101110101011011010010000001110100011010010110001101101011 1
#160000
0%
#165000
0!
b110 ,
0$
0/
1%
#166000
b10001 (
b1000001 '
b11011010110100101101110011010010110110101110101011011010010000001110100011010010110001101101011 1
#170000
0%
#175000
1!
1$
1/
b111 ,
1%
#176000
b10010 (
b1000101 '
b11011010110100101101110011010010110110101110101011011010010000001110100011010010110001101101011 1
#180000
0%
#185000
0!
b1000 ,
0$
0/
1%
#186000
b10011 (
b1001001 '
b11011010110100101101110011010010110110101110101011011010010000001110100011010010110001101101011 1
#190000
0%
#195000
1!
1"
1$
1/
b1001 ,
1%
#196000
b10100 (
b1001101 '
b11011010110100101101110011010010110110101110101011011010010000001110100011010010110001101101011 1
#200000
0%
#205000
0"
0!
0#
b0 ,
0$
0/
b10 )
1%
#206000
b10101 (
b1010001 '
b11011010110100101101110011010010110110101110101011011010010000001110100011010010110001101101011 1
#210000
0%
#215000
1!
1$
1/
b1 ,
1%
#216000
b10110 (
b1010101 '
b11011010110100101101110011010010110110101110101011011010010000001110100011010010110001101101011 1
#220000
0%
#225000
0!
b10 ,
0$
0/
1%
#226000
b10111 (
b1011001 '
b11011010110100101101110011010010110110101110101011011010010000001110100011010010110001101101011 1
#230000
0%
#235000
1!
1$
1/
b11 ,
1%
#236000
b11000 (
b1011101 '
b11011010110100101101110011010010110110101110101011011010010000001110100011010010110001101101011 1
#240000
0%
#245000
0!
b100 ,
0$
0/
1%
#246000
b11001 (
b1100001 '
b11011010110100101101110011010010110110101110101011011010010000001110100011010010110001101101011 1
#250000
0%
#255000
1!
1$
1/
1#
b101 ,
1%
#256000
b11010 (
b1100101 '
b11011010110100101101110011010010110110101110101011011010010000001110100011010010110001101101011 1
#260000
0%
#265000
0!
b110 ,
0$
0/
1%
#266000
b11011 (
b1101001 '
b11011010110100101101110011010010110110101110101011011010010000001110100011010010110001101101011 1
#270000
0%
#275000
1!
1$
1/
b111 ,
1%
#276000
b11100 (
b1101101 '
b11011010110100101101110011010010110110101110101011011010010000001110100011010010110001101101011 1
#280000
0%
#285000
0!
b1000 ,
0$
0/
1%
#286000
b11101 (
b1110001 '
b11011010110100101101110011010010110110101110101011011010010000001110100011010010110001101101011 1
#290000
0%
#295000
1!
1"
1$
1/
b1001 ,
1%
#296000
b11110 (
b1110101 '
b11011010110100101101110011010010110110101110101011011010010000001110100011010010110001101101011 1
#300000
0%
#305000
0"
0!
0#
b0 ,
0$
0/
b11 )
1%
#306000
b11111 (
b1111010 '
b111010001101000011100100110010101100101001000000110001101101111011011100111001101110101011011010110010101100100001000000110010101101110011000010110001001101100011001010111001100100000011010010110111000100000001100110011000000100000011000110110110001101111011000110110101101110011 1
#310000
0%
#315000
1!
1$
1/
b1 ,
1%
#320000
0%
#325000
0!
b10 ,
0$
0/
1%
#330000
0%
#335000
1!
1$
1/
b11 ,
1%
#340000
0%
#345000
0!
b100 ,
0$
0/
1%
#350000
0%
#355000
1!
1$
1/
1#
b101 ,
1%
#360000
0%
#365000
0!
b110 ,
0$
0/
1%
#370000
0%
#375000
1!
1$
1/
b111 ,
1%
#376000
0!
1&
#377000
b1111011 '
b1110010011001010111001101100101011101000010000001101101011000010111001101101011011100110010000001110100011010010110001101101011001000000110001001100101011001100110111101110010011001010010000001100101011001000110011101100101 1
#380000
0%
#385000
0#
b0 ,
0$
0/
1%
#386000
0&
b1111100 '
b1110010011001010111001101100101011101000010000001101101011010010110010000100000011100000110010101110010011010010110111101100100 1
#390000
0%
#395000
1!
1$
1/
b1 ,
1%
#396000
b1111101 '
b1110010011001010111001101110100011000010111001001110100001000000110110001101111011101110010000001101000011000010110110001100110 1
#400000
0%
#405000
0!
b10 ,
0$
0/
1%
#406000
b1111110 '
#410000
0%
#415000
1!
1$
1/
b11 ,
1%
#416000
b1111111 '
#420000
0%
#425000
0!
b100 ,
0$
0/
1%
#426000
b10000000 '
#430000
0%
#435000
1!
1$
1/
1#
b101 ,
1%
#436000
b10000001 '
b11100100110010101110011011101000110000101110010011101000010000001100110011010010111001001110011011101000010000001110100011100100110000101101110011100110110100101110100011010010110111101101110 1
